git_annex_adapter/__init__.py
git_annex_adapter/exceptions.py
git_annex_adapter/process.py
git_annex_adapter/repo.py
git_annex_adapter-0.2.2.dist-info/LICENSE
git_annex_adapter-0.2.2.dist-info/METADATA
git_annex_adapter-0.2.2.dist-info/WHEEL
git_annex_adapter-0.2.2.dist-info/top_level.txt
git_annex_adapter-0.2.2.dist-info/RECORD
