Metadata-Version: 2.1
Name: git-annex-adapter
Version: 0.2.2
Summary: Call git-annex commands from Python
Home-page: https://github.com/alpernebbi/git-annex-adapter
Author: Alper Nebi Yasak
Author-email: alpernebiyasak@gmail.com
License: GPL3+
Keywords: git-annex metadata
Platform: UNKNOWN
Classifier: Development Status :: 3 - Alpha
Classifier: Intended Audience :: Developers
Classifier: Topic :: Software Development :: Libraries
Classifier: License :: OSI Approved :: GNU General Public License v3 or later (GPLv3+)
Classifier: Programming Language :: Python :: 3
Classifier: Programming Language :: Python :: 3.5
Requires-Dist: pygit2
